[
    [
        {
            "tag": "breeze",
            "files": {
                "highlight.svg": "assets/highlight.svg.in",
                "radio.svg": "assets/radio.svg",
                "arrow.svg": "assets/arrow.svg"
            }
        }
    ],
    [
        {
            "tag": "opaque",
            "files": {
                "panel.svg": "assets/panel.svg.in",
                "theme.conf": "config/theme.conf.in"
            }
        },
        {
            "tag": "translucent",
            "files": {
                "panel.svg": "assets/panel_translucent.svg.in",
                "theme.conf": "config/theme_translucent.conf.in"
            }
        }
    ],
    [
        {
            "tag": "light",
            "variables": {
                "BACKGROUND_COLOR": "#eff0f1",
                "BACKGROUND_COLOR_NAME": "light",
                "BACKGROUND_COLOR_NAME_ZH": "亮色",
                "NORMAL_COLOR": "#232629",
                "HIGHLIGHT_COLOR": "#eff0f1"
            },
            "files": {
                "prev.svg": "assets/prev_light.svg",
                "next.svg": "assets/next_light.svg"
            }
        },
        {
            "tag": "dark",
            "variables": {
                "BACKGROUND_COLOR": "#31363b",
                "BACKGROUND_COLOR_NAME": "dark",
                "BACKGROUND_COLOR_NAME_ZH": "暗色",
                "NORMAL_COLOR": "#fcfcfc",
                "HIGHLIGHT_COLOR": "#202428"
            },
            "files": {
                "prev.svg": "assets/prev_dark.svg",
                "next.svg": "assets/next_dark.svg"
            }
        }
    ],
    [
        {
            "tag": "blue",
            "variables": {
                "ACCENT_COLOR": "#3daee9",
                "ACCENT_COLOR_NAME": "Blue",
                "ACCENT_COLOR_NAME_ZH": "蓝色"
            }
        },
        {
            "tag": "mint",
            "variables": {
                "ACCENT_COLOR": "#2db496",
                "ACCENT_COLOR_NAME": "Mint",
                "ACCENT_COLOR_NAME_ZH": "青色"
            }
        },
        {
            "tag": "purple",
            "variables": {
                "ACCENT_COLOR": "#c0afea",
                "ACCENT_COLOR_NAME": "Purple",
                "ACCENT_COLOR_NAME_ZH": "紫色"
            }
        },
        {
            "tag": "pink",
            "variables": {
                "ACCENT_COLOR": "#ec95c5",
                "ACCENT_COLOR_NAME": "Pink",
                "ACCENT_COLOR_NAME_ZH": "粉色"
            }
        }
    ]
]
